LICENSE
README.md
setup.py
SimpleAxel_Pay.egg-info/PKG-INFO
SimpleAxel_Pay.egg-info/SOURCES.txt
SimpleAxel_Pay.egg-info/dependency_links.txt
SimpleAxel_Pay.egg-info/top_level.txt
pay/__init__.py
pay/main.py