Metadata-Version: 2.1
Name: SimpleAxel-Pay
Version: 0.0.2
Summary: Pay blueprint for SimpleAxel (https://git.tech.eus/EuskadiTech/SimpleAxel-Pay)
Home-page: https://git.tech.eus/EuskadiTech/SimpleAxel-Pay
Author: EuskadiTech
Classifier: Development Status :: 3 - Alpha
Classifier: Intended Audience :: Developers
Classifier: Programming Language :: Python :: 3
Requires: requests
Requires: Flask
Requires: stripe
Requires: SimpleSDK
License-File: LICENSE
